violent_webdriver/Chrome.py
violent_webdriver/__init__.py
violent_webdriver-1.0.28.dist-info/LICENSE
violent_webdriver-1.0.28.dist-info/METADATA
violent_webdriver-1.0.28.dist-info/WHEEL
violent_webdriver-1.0.28.dist-info/top_level.txt
violent_webdriver-1.0.28.dist-info/RECORD
