Metadata-Version: 2.1
Name: violent-webdriver
Version: 1.0.28
Summary: violent webdriver based on selenium
Home-page: https://github.com/amazingTest/violent-webdriver
Author: Yuyi Shao
Author-email: 523314409@qq.com
License: UNKNOWN
Platform: UNKNOWN
Classifier: Programming Language :: Python :: 3
Classifier: License :: OSI Approved :: MIT License
Classifier: Operating System :: OS Independent
